{
  "gatherDate": "2024-12-05T14:38:30",
  "dateRange": {
    "start": "2024-11-25T01:00:00",
    "end": "2025-01-20T01:00:00"
  },
  "items": [
    {
      "title": "Workshops Open Dag",
      "start": "2024-12-06T08:30:00",
      "end": "2024-12-06T16:00:00",
      "extendedProps": {
        "groups": [],
        "rooms": [
          "ZP11/D1.07"
        ],
        "lecturers": [
          "R Wedema (WERD)"
        ]
      }
    },
    {
      "title": "BFVP22GENEN/Tussen Genen en Genezen",
      "start": "2024-11-25T08:30:00",
      "end": "2024-11-25T12:30:00",
      "extendedProps": {
        "groups": [
          "BFV1"
        ],
        "rooms": [
          "ZP11/D1.08"
        ],
        "lecturers": [
          "AM Poortinga (PARN)"
        ]
      }
    },
    {
      "title": "BFVP24BIOCHBEEL/Biochemie in Beeld",
      "start": "2024-11-25T12:30:00",
      "end": "2024-11-25T16:30:00",
      "extendedProps": {
        "groups": [
          "BFV1"
        ],
        "rooms": [
          "ZP11/D1.08"
        ],
        "lecturers": [
          "L Oldhoff (OLLO)"
        ]
      }
    },
    {
      "title": "BFVP24BIOCHBEEL/Biochemie in Beeld",
      "start": "2024-11-27T08:30:00",
      "end": "2024-11-27T12:30:00",
      "extendedProps": {
        "groups": [
          "BFV1"
        ],
        "rooms": [
          "ZP11/D1.08"
        ],
        "lecturers": [
          "SM Nabuurs (NASA)"
        ]
      }
    },
    {
      "title": "BFVP22GENEN/Tussen Genen en Genezen",
      "start": "2024-11-27T12:30:00",
      "end": "2024-11-27T16:30:00",
      "extendedProps": {
        "groups": [
          "BFV1"
        ],
        "rooms": [
          "ZP11/D1.08"
        ],
        "lecturers": [
          "R Wedema (WERD)"
        ]
      }
    },
    {
      "title": "BFVP24BIOCHBEEL/Biochemie in Beeld",
      "start": "2024-11-28T08:30:00",
      "end": "2024-11-28T12:30:00",
      "extendedProps": {
        "groups": [
          "BFV1"
        ],
        "rooms": [
          "ZP11/D1.08"
        ],
        "lecturers": [
          "SM Nabuurs (NASA)"
        ]
      }
    },
    {
      "title": "BFVP24BIOCHBEEL/Biochemie in Beeld",
      "start": "2024-11-29T12:30:00",
      "end": "2024-11-29T16:30:00",
      "extendedProps": {
        "groups": [
          "BFV1"
        ],
        "rooms": [
          "ZP11/D1.08"
        ],
        "lecturers": [
          "L Oldhoff (OLLO)"
        ]
      }
    },
    {
      "title": "BFVP22GENEN/Tussen Genen en Genezen",
      "start": "2024-12-02T08:30:00",
      "end": "2024-12-02T12:30:00",
      "extendedProps": {
        "groups": [
          "BFV1"
        ],
        "rooms": [
          "ZP11/D1.08"
        ],
        "lecturers": [
          "AM Poortinga (PARN)"
        ]
      }
    },
    {
      "title": "BFVP24BIOCHBEEL/Biochemie in Beeld",
      "start": "2024-12-02T12:30:00",
      "end": "2024-12-02T16:30:00",
      "extendedProps": {
        "groups": [
          "BFV1"
        ],
        "rooms": [
          "ZP11/D1.08"
        ],
        "lecturers": [
          "L Oldhoff (OLLO)"
        ]
      }
    },
    {
      "title": "BFVP24BIOCHBEEL/Biochemie in Beeld",
      "start": "2024-12-04T08:30:00",
      "end": "2024-12-04T12:30:00",
      "extendedProps": {
        "groups": [
          "BFV1"
        ],
        "rooms": [
          "ZP11/D1.08"
        ],
        "lecturers": [
          "L Oldhoff (OLLO)"
        ]
      }
    },
    {
      "title": "BFVP22GENEN/Tussen Genen en Genezen",
      "start": "2024-12-04T12:30:00",
      "end": "2024-12-04T16:30:00",
      "extendedProps": {
        "groups": [
          "BFV1"
        ],
        "rooms": [
          "ZP11/D1.08"
        ],
        "lecturers": [
          "R Wedema (WERD)"
        ]
      }
    },
    {
      "title": "BFVP24BIOCHBEEL/Biochemie in Beeld",
      "start": "2024-12-05T08:30:00",
      "end": "2024-12-05T12:30:00",
      "extendedProps": {
        "groups": [
          "BFV1"
        ],
        "rooms": [
          "ZP11/D1.08"
        ],
        "lecturers": [
          "SM Nabuurs (NASA)"
        ]
      }
    },
    {
      "title": "BFVP24BIOCHBEEL/Biochemie in Beeld",
      "start": "2024-12-06T12:30:00",
      "end": "2024-12-06T16:30:00",
      "extendedProps": {
        "groups": [
          "BFV1"
        ],
        "rooms": [
          "ZP11/D1.08"
        ],
        "lecturers": [
          "SM Nabuurs (NASA)"
        ]
      }
    },
    {
      "title": "BFVP22GENEN/Tussen Genen en Genezen",
      "start": "2024-12-09T08:30:00",
      "end": "2024-12-09T12:30:00",
      "extendedProps": {
        "groups": [
          "BFV1"
        ],
        "rooms": [
          "ZP11/D1.08"
        ],
        "lecturers": [
          "AM Poortinga (PARN)"
        ]
      }
    },
    {
      "title": "BFVP24BIOCHBEEL/Biochemie in Beeld",
      "start": "2024-12-09T12:30:00",
      "end": "2024-12-09T16:30:00",
      "extendedProps": {
        "groups": [
          "BFV1"
        ],
        "rooms": [
          "ZP11/D1.08"
        ],
        "lecturers": [
          "L Oldhoff (OLLO)"
        ]
      }
    },
    {
      "title": "BFVP24BIOCHBEEL/Biochemie in Beeld",
      "start": "2024-12-11T08:30:00",
      "end": "2024-12-11T12:30:00",
      "extendedProps": {
        "groups": [
          "BFV1"
        ],
        "rooms": [
          "ZP11/D1.08"
        ],
        "lecturers": [
          "L Oldhoff (OLLO)"
        ]
      }
    },
    {
      "title": "BFVP22GENEN/Tussen Genen en Genezen",
      "start": "2024-12-11T14:30:00",
      "end": "2024-12-11T16:30:00",
      "extendedProps": {
        "groups": [
          "BFV1"
        ],
        "rooms": [
          "ZP11/D1.08"
        ],
        "lecturers": [
          "R Wedema (WERD)"
        ]
      }
    },
    {
      "title": "BFVP24BIOCHBEEL/Biochemie in Beeld",
      "start": "2024-12-12T08:30:00",
      "end": "2024-12-12T12:30:00",
      "extendedProps": {
        "groups": [
          "BFV1"
        ],
        "rooms": [
          "ZP11/D1.08"
        ],
        "lecturers": [
          "SM Nabuurs (NASA)"
        ]
      }
    },
    {
      "title": "BFVP24BIOCHBEEL/Biochemie in Beeld",
      "start": "2024-12-13T08:30:00",
      "end": "2024-12-13T12:30:00",
      "extendedProps": {
        "groups": [
          "BFV1"
        ],
        "rooms": [
          "ZP11/D1.08"
        ],
        "lecturers": [
          "SM Nabuurs (NASA)"
        ]
      }
    },
    {
      "title": "BFVP22GENEN/Tussen Genen en Genezen",
      "start": "2024-12-16T08:30:00",
      "end": "2024-12-16T12:30:00",
      "extendedProps": {
        "groups": [
          "BFV1"
        ],
        "rooms": [
          "ZP11/D1.08"
        ],
        "lecturers": [
          "AM Poortinga (PARN)"
        ]
      }
    },
    {
      "title": "BFVP24BIOCHBEEL/Biochemie in Beeld",
      "start": "2024-12-16T12:30:00",
      "end": "2024-12-16T16:30:00",
      "extendedProps": {
        "groups": [
          "BFV1"
        ],
        "rooms": [
          "ZP11/D1.08"
        ],
        "lecturers": [
          "L Oldhoff (OLLO)"
        ]
      }
    },
    {
      "title": "BFVP24BIOCHBEEL/Biochemie in Beeld",
      "start": "2024-12-18T08:30:00",
      "end": "2024-12-18T12:30:00",
      "extendedProps": {
        "groups": [
          "BFV1"
        ],
        "rooms": [
          "ZP11/D1.08"
        ],
        "lecturers": [
          "SM Nabuurs (NASA)"
        ]
      }
    },
    {
      "title": "BFVP22GENEN/Tussen Genen en Genezen",
      "start": "2024-12-18T12:30:00",
      "end": "2024-12-18T15:30:00",
      "extendedProps": {
        "groups": [
          "BFV1"
        ],
        "rooms": [
          "ZP11/D1.08"
        ],
        "lecturers": [
          "R Wedema (WERD)"
        ]
      }
    },
    {
      "title": "Klassengesprek/Klassengesprek BFV1",
      "start": "2024-12-18T15:30:00",
      "end": "2024-12-18T16:30:00",
      "extendedProps": {
        "groups": [
          "BFV1"
        ],
        "rooms": [
          "ZP11/D1.08"
        ],
        "lecturers": [
          "MA Noback (NOMI)",
          "IM van der Veen (VEID)"
        ]
      }
    },
    {
      "title": "BFVP24BIOCHBEEL/Biochemie in Beeld",
      "start": "2024-12-19T08:30:00",
      "end": "2024-12-19T12:30:00",
      "extendedProps": {
        "groups": [
          "BFV1"
        ],
        "rooms": [
          "ZP11/D1.08"
        ],
        "lecturers": [
          "SM Nabuurs (NASA)"
        ]
      }
    },
    {
      "title": "BFVP24BIOCHBEEL/Biochemie in Beeld",
      "start": "2024-12-20T08:30:00",
      "end": "2024-12-20T12:30:00",
      "extendedProps": {
        "groups": [
          "BFV1"
        ],
        "rooms": [
          "ZP11/D1.08"
        ],
        "lecturers": [
          "L Oldhoff (OLLO)"
        ]
      }
    },
    {
      "title": "BFVP22GENEN/Tussen Genen en Genezen",
      "start": "2025-01-06T08:30:00",
      "end": "2025-01-06T12:30:00",
      "extendedProps": {
        "groups": [
          "BFV1"
        ],
        "rooms": [
          "ZP11/D1.08"
        ],
        "lecturers": [
          "AM Poortinga (PARN)"
        ]
      }
    },
    {
      "title": "BFVP24BIOCHBEEL/Biochemie in Beeld",
      "start": "2025-01-06T12:30:00",
      "end": "2025-01-06T16:30:00",
      "extendedProps": {
        "groups": [
          "BFV1"
        ],
        "rooms": [
          "ZP11/D1.08"
        ],
        "lecturers": [
          "L Oldhoff (OLLO)"
        ]
      }
    },
    {
      "title": "BFVP24BIOCHBEEL/Biochemie in Beeld",
      "start": "2025-01-08T08:30:00",
      "end": "2025-01-08T12:30:00",
      "extendedProps": {
        "groups": [
          "BFV1"
        ],
        "rooms": [
          "ZP11/D1.08"
        ],
        "lecturers": [
          "L Oldhoff (OLLO)"
        ]
      }
    },
    {
      "title": "BFVP22GENEN/Tussen Genen en Genezen",
      "start": "2025-01-08T12:30:00",
      "end": "2025-01-08T16:30:00",
      "extendedProps": {
        "groups": [
          "BFV1"
        ],
        "rooms": [
          "ZP11/D1.08"
        ],
        "lecturers": [
          "R Wedema (WERD)"
        ]
      }
    },
    {
      "title": "BFVP24BIOCHBEEL/Biochemie in Beeld",
      "start": "2025-01-09T08:30:00",
      "end": "2025-01-09T12:30:00",
      "extendedProps": {
        "groups": [
          "BFV1"
        ],
        "rooms": [
          "ZP11/D1.08"
        ],
        "lecturers": [
          "SM Nabuurs (NASA)"
        ]
      }
    },
    {
      "title": "BFVP24BIOCHBEEL/Biochemie in Beeld",
      "start": "2025-01-10T08:30:00",
      "end": "2025-01-10T12:30:00",
      "extendedProps": {
        "groups": [
          "BFV1"
        ],
        "rooms": [
          "ZP11/D1.08"
        ],
        "lecturers": [
          "SM Nabuurs (NASA)"
        ]
      }
    },
    {
      "title": "BFVP22GENEN/Tussen Genen en Genezen",
      "start": "2025-01-13T08:30:00",
      "end": "2025-01-13T12:30:00",
      "extendedProps": {
        "groups": [
          "BFV1"
        ],
        "rooms": [
          "ZP11/D1.08"
        ],
        "lecturers": [
          "AM Poortinga (PARN)"
        ]
      }
    },
    {
      "title": "BFVP24BIOCHBEEL/Biochemie in Beeld",
      "start": "2025-01-13T12:30:00",
      "end": "2025-01-13T16:30:00",
      "extendedProps": {
        "groups": [
          "BFV1"
        ],
        "rooms": [
          "ZP11/D1.08"
        ],
        "lecturers": [
          "L Oldhoff (OLLO)"
        ]
      }
    },
    {
      "title": "BFVP24BIOCHBEEL/Biochemie in Beeld",
      "start": "2025-01-15T08:30:00",
      "end": "2025-01-15T12:30:00",
      "extendedProps": {
        "groups": [
          "BFV1"
        ],
        "rooms": [
          "ZP11/D1.08"
        ],
        "lecturers": [
          "L Oldhoff (OLLO)"
        ]
      }
    },
    {
      "title": "BFVP22GENEN/Tussen Genen en Genezen",
      "start": "2025-01-15T12:30:00",
      "end": "2025-01-15T16:30:00",
      "extendedProps": {
        "groups": [
          "BFV1"
        ],
        "rooms": [
          "ZP11/D1.08"
        ],
        "lecturers": [
          "R Wedema (WERD)"
        ]
      }
    },
    {
      "title": "BFVP24BIOCHBEEL/Biochemie in Beeld",
      "start": "2025-01-16T08:30:00",
      "end": "2025-01-16T12:30:00",
      "extendedProps": {
        "groups": [
          "BFV1"
        ],
        "rooms": [
          "ZP11/D1.08"
        ],
        "lecturers": [
          "SM Nabuurs (NASA)"
        ]
      }
    },
    {
      "title": "Vragenuur/nabespr.tent. Van DNA tot ",
      "start": "2025-01-16T12:30:00",
      "end": "2025-01-16T14:30:00",
      "extendedProps": {
        "groups": [
          "BFV1"
        ],
        "rooms": [
          "ZP11/D1.08"
        ],
        "lecturers": [
          "TE Vrenken (VRTI)"
        ]
      }
    },
    {
      "title": "BFVP24BIOCHBEEL/Biochemie in Beeld",
      "start": "2025-01-17T08:30:00",
      "end": "2025-01-17T12:30:00",
      "extendedProps": {
        "groups": [
          "BFV1"
        ],
        "rooms": [
          "ZP11/D1.08"
        ],
        "lecturers": [
          "SM Nabuurs (NASA)"
        ]
      }
    },
    {
      "title": "BFVH24MODELLERE/Mod. van Kanker Casus A",
      "start": "2024-11-25T08:30:00",
      "end": "2024-11-25T12:30:00",
      "extendedProps": {
        "groups": [
          "BFV3"
        ],
        "rooms": [
          "ZP11/H1.122"
        ],
        "lecturers": [
          "DRM Langers (LADR)"
        ]
      }
    },
    {
      "title": "BFVH24BIOCANCER/Biology of Cancer",
      "start": "2024-11-26T12:30:00",
      "end": "2024-11-26T16:30:00",
      "extendedProps": {
        "groups": [
          "BFV3"
        ],
        "rooms": [
          "ZP11/D1.08"
        ],
        "lecturers": [
          "WA Pool (POWE)"
        ]
      }
    },
    {
      "title": "BFVH24MODELLERE/Mod. van Kanker Casus B",
      "start": "2024-11-27T12:30:00",
      "end": "2024-11-27T16:30:00",
      "extendedProps": {
        "groups": [
          "BFV3"
        ],
        "rooms": [
          "ZP11/H1.122"
        ],
        "lecturers": [
          "B Barnard (BABA)"
        ]
      }
    },
    {
      "title": "BFVH24MODELLERE/Mod. van Kanker Casus B",
      "start": "2024-11-28T08:30:00",
      "end": "2024-11-28T12:30:00",
      "extendedProps": {
        "groups": [
          "BFV3"
        ],
        "rooms": [
          "ZP11/H1.122"
        ],
        "lecturers": [
          "B Barnard (BABA)"
        ]
      }
    },
    {
      "title": "BFVH24MODELLERE/Mod. van Kanker Casus B",
      "start": "2024-11-29T12:30:00",
      "end": "2024-11-29T16:30:00",
      "extendedProps": {
        "groups": [
          "BFV3"
        ],
        "rooms": [
          "ZP11/H1.122"
        ],
        "lecturers": [
          "B Barnard (BABA)"
        ]
      }
    },
    {
      "title": "BFVH24MODELLERE/Mod. van Kanker Casus B",
      "start": "2024-12-02T08:30:00",
      "end": "2024-12-02T12:30:00",
      "extendedProps": {
        "groups": [
          "BFV3"
        ],
        "rooms": [
          "ZP11/H1.122"
        ],
        "lecturers": [
          "B Barnard (BABA)"
        ]
      }
    },
    {
      "title": "BFVH24BIOCANCER/Biology of Cancer",
      "start": "2024-12-03T12:30:00",
      "end": "2024-12-03T16:30:00",
      "extendedProps": {
        "groups": [
          "BFV3"
        ],
        "rooms": [
          "ZP11/D1.08"
        ],
        "lecturers": [
          "TE Vrenken (VRTI)"
        ]
      }
    },
    {
      "title": "BFVH24MODELLERE/Mod. van Kanker Casus B",
      "start": "2024-12-04T12:30:00",
      "end": "2024-12-04T16:30:00",
      "extendedProps": {
        "groups": [
          "BFV3"
        ],
        "rooms": [
          "ZP11/H1.122"
        ],
        "lecturers": [
          "B Barnard (BABA)"
        ]
      }
    },
    {
      "title": "BFVH24MODELLERE/Mod. van Kanker Casus C",
      "start": "2024-12-05T08:30:00",
      "end": "2024-12-05T12:30:00",
      "extendedProps": {
        "groups": [
          "BFV3"
        ],
        "rooms": [
          "ZP11/H1.122"
        ],
        "lecturers": [
          "DRM Langers (LADR)"
        ]
      }
    },
    {
      "title": "BFVH24MODELLERE/Mod. van Kanker Casus C",
      "start": "2024-12-06T12:30:00",
      "end": "2024-12-06T16:30:00",
      "extendedProps": {
        "groups": [
          "BFV3"
        ],
        "rooms": [
          "ZP11/H1.122"
        ],
        "lecturers": [
          "DRM Langers (LADR)"
        ]
      }
    },
    {
      "title": "BFVH24MODELLERE/Mod. van Kanker Casus C",
      "start": "2024-12-09T08:30:00",
      "end": "2024-12-09T12:30:00",
      "extendedProps": {
        "groups": [
          "BFV3"
        ],
        "rooms": [
          "ZP11/H1.122"
        ],
        "lecturers": [
          "DRM Langers (LADR)"
        ]
      }
    },
    {
      "title": "BFVH24MODELLERE/Mod. van Kanker Casus C",
      "start": "2024-12-10T08:30:00",
      "end": "2024-12-10T12:30:00",
      "extendedProps": {
        "groups": [
          "BFV3"
        ],
        "rooms": [
          "ZP11/D1.08"
        ],
        "lecturers": [
          "DRM Langers (LADR)"
        ]
      }
    },
    {
      "title": "BFVH24BIOCANCER/Biology of Cancer",
      "start": "2024-12-10T12:30:00",
      "end": "2024-12-10T16:30:00",
      "extendedProps": {
        "groups": [
          "BFV3"
        ],
        "rooms": [
          "ZP11/D1.08"
        ],
        "lecturers": [
          "SM Nabuurs (NASA)",
          "TE Vrenken (VRTI)"
        ]
      }
    },
    {
      "title": "BFVH24MODELLERE/Mod. van Kanker Casus C",
      "start": "2024-12-12T08:30:00",
      "end": "2024-12-12T12:30:00",
      "extendedProps": {
        "groups": [
          "BFV3"
        ],
        "rooms": [
          "ZP11/H1.122"
        ],
        "lecturers": [
          "DRM Langers (LADR)"
        ]
      }
    },
    {
      "title": "BFVH24MODELLERE/Mod. van Kanker Casus D",
      "start": "2024-12-13T12:30:00",
      "end": "2024-12-13T16:30:00",
      "extendedProps": {
        "groups": [
          "BFV3"
        ],
        "rooms": [
          "ZP11/H1.122"
        ],
        "lecturers": [
          "B Barnard (BABA)"
        ]
      }
    },
    {
      "title": "BFVH24BIOCANCER/Gast-college",
      "start": "2024-12-17T12:30:00",
      "end": "2024-12-17T16:30:00",
      "extendedProps": {
        "groups": [
          "BFV3"
        ],
        "rooms": [
          "ZP11/D1.08"
        ],
        "lecturers": [
          "WA Pool (POWE)",
          "TE Vrenken (VRTI)"
        ]
      }
    },
    {
      "title": "BFVH24MODELLERE/Mod. van Kanker Casus D",
      "start": "2024-12-18T12:30:00",
      "end": "2024-12-18T16:30:00",
      "extendedProps": {
        "groups": [
          "BFV3"
        ],
        "rooms": [
          "ZP11/H1.122"
        ],
        "lecturers": [
          "B Barnard (BABA)"
        ]
      }
    },
    {
      "title": "BFVH24MODELLERE/Mod. van Kanker Casus D",
      "start": "2024-12-19T08:30:00",
      "end": "2024-12-19T12:30:00",
      "extendedProps": {
        "groups": [
          "BFV3"
        ],
        "rooms": [
          "ZP11/H1.122"
        ],
        "lecturers": [
          "B Barnard (BABA)"
        ]
      }
    },
    {
      "title": "BFVH24MODELLERE/Mod. van Kanker Casus D",
      "start": "2024-12-19T12:30:00",
      "end": "2024-12-19T16:30:00",
      "extendedProps": {
        "groups": [
          "BFV3"
        ],
        "rooms": [
          "ZP11/D1.08"
        ],
        "lecturers": [
          "B Barnard (BABA)"
        ]
      }
    },
    {
      "title": "BFVH24MODELLERE/Mod. van Kanker Casus D",
      "start": "2024-12-20T12:30:00",
      "end": "2024-12-20T16:30:00",
      "extendedProps": {
        "groups": [
          "BFV3"
        ],
        "rooms": [
          "ZP11/H1.122"
        ],
        "lecturers": [
          "B Barnard (BABA)"
        ]
      }
    },
    {
      "title": "BFVH24MODELLERE/Mod. van Kanker Project",
      "start": "2025-01-06T08:30:00",
      "end": "2025-01-06T12:30:00",
      "extendedProps": {
        "groups": [
          "BFV3"
        ],
        "rooms": [
          "ZP11/H1.122"
        ],
        "lecturers": [
          "TA Wassenaar (WATS)"
        ]
      }
    },
    {
      "title": "BFVH24MODELLERE/Mod. van Kanker Project",
      "start": "2025-01-07T08:30:00",
      "end": "2025-01-07T12:30:00",
      "extendedProps": {
        "groups": [
          "BFV3"
        ],
        "rooms": [
          "ZP11/D1.08"
        ],
        "lecturers": [
          "TA Wassenaar (WATS)"
        ]
      }
    },
    {
      "title": "BFVH24BIOCANCER/Biology of Cancer",
      "start": "2025-01-07T12:30:00",
      "end": "2025-01-07T16:30:00",
      "extendedProps": {
        "groups": [
          "BFV3"
        ],
        "rooms": [
          "ZP11/D1.08"
        ],
        "lecturers": [
          "TE Vrenken (VRTI)"
        ]
      }
    },
    {
      "title": "BFVH24MODELLERE/Mod. van Kanker Project",
      "start": "2025-01-09T08:30:00",
      "end": "2025-01-09T12:30:00",
      "extendedProps": {
        "groups": [
          "BFV3"
        ],
        "rooms": [
          "ZP11/H1.122"
        ],
        "lecturers": [
          "TA Wassenaar (WATS)"
        ]
      }
    },
    {
      "title": "BFVH24MODELLERE/Mod. van Kanker Project",
      "start": "2025-01-10T12:30:00",
      "end": "2025-01-10T16:30:00",
      "extendedProps": {
        "groups": [
          "BFV3"
        ],
        "rooms": [
          "ZP11/H1.122"
        ],
        "lecturers": [
          "TA Wassenaar (WATS)"
        ]
      }
    },
    {
      "title": "BFVH24MODELLERE/Mod. van Kanker Project",
      "start": "2025-01-13T08:30:00",
      "end": "2025-01-13T12:30:00",
      "extendedProps": {
        "groups": [
          "BFV3"
        ],
        "rooms": [
          "ZP11/H1.122"
        ],
        "lecturers": [
          "TA Wassenaar (WATS)"
        ]
      }
    },
    {
      "title": "BFVH24MODELLERE/Mod. van Kanker Project",
      "start": "2025-01-14T08:30:00",
      "end": "2025-01-14T12:30:00",
      "extendedProps": {
        "groups": [
          "BFV3"
        ],
        "rooms": [
          "ZP11/D1.08"
        ],
        "lecturers": [
          "TA Wassenaar (WATS)"
        ]
      }
    },
    {
      "title": "BFVH24BIOCANCER/Biology of Cancer",
      "start": "2025-01-14T12:30:00",
      "end": "2025-01-14T16:30:00",
      "extendedProps": {
        "groups": [
          "BFV3"
        ],
        "rooms": [
          "ZP11/D1.08"
        ],
        "lecturers": [
          "WA Pool (POWE)"
        ]
      }
    },
    {
      "title": "BFVH24MODELLERE/Mod. van Kanker Project",
      "start": "2025-01-16T08:30:00",
      "end": "2025-01-16T12:30:00",
      "extendedProps": {
        "groups": [
          "BFV3"
        ],
        "rooms": [
          "ZP11/H1.122"
        ],
        "lecturers": [
          "TA Wassenaar (WATS)"
        ]
      }
    },
    {
      "title": "BFVH24MODELLERE/Mod. van Kanker Project",
      "start": "2025-01-17T12:30:00",
      "end": "2025-01-17T16:30:00",
      "extendedProps": {
        "groups": [
          "BFV3"
        ],
        "rooms": [
          "ZP11/H1.122"
        ],
        "lecturers": [
          "TA Wassenaar (WATS)"
        ]
      }
    },
    {
      "title": "BFVH23DATADASH/Datadashboards",
      "start": "2024-11-25T12:30:00",
      "end": "2024-11-25T16:30:00",
      "extendedProps": {
        "groups": [
          "BFV2"
        ],
        "rooms": [
          "ZP11/H1.122"
        ],
        "lecturers": [
          "AM Poortinga (PARN)"
        ]
      }
    },
    {
      "title": "BFVH23DATADASH/Datadashboards",
      "start": "2024-11-26T08:30:00",
      "end": "2024-11-26T12:30:00",
      "extendedProps": {
        "groups": [
          "BFV2"
        ],
        "rooms": [
          "ZP11/H1.122"
        ],
        "lecturers": [
          "MA Noback (NOMI)"
        ]
      }
    },
    {
      "title": "BFVH23IMMUNO/Immunologie",
      "start": "2024-11-26T12:30:00",
      "end": "2024-11-26T16:30:00",
      "extendedProps": {
        "groups": [
          "BFV2"
        ],
        "rooms": [
          "ZP11/H1.122"
        ],
        "lecturers": [
          "L Oldhoff (OLLO)"
        ]
      }
    },
    {
      "title": "BFVH23DATADASH/Datadashboards",
      "start": "2024-11-27T08:30:00",
      "end": "2024-11-27T12:30:00",
      "extendedProps": {
        "groups": [
          "BFV2"
        ],
        "rooms": [
          "ZP11/H1.122"
        ],
        "lecturers": [
          "B Barnard (BABA)"
        ]
      }
    },
    {
      "title": "BFVH23DATADASH/Datadashboards",
      "start": "2024-11-28T12:30:00",
      "end": "2024-11-28T16:00:00",
      "extendedProps": {
        "groups": [
          "BFV2"
        ],
        "rooms": [
          "ZP11/D1.08"
        ],
        "lecturers": [
          "B Barnard (BABA)"
        ]
      }
    },
    {
      "title": "BFVH23IMMUNO/Immunologie",
      "start": "2024-11-29T08:30:00",
      "end": "2024-11-29T12:30:00",
      "extendedProps": {
        "groups": [
          "BFV2"
        ],
        "rooms": [
          "ZP11/H1.122"
        ],
        "lecturers": [
          "SM Nabuurs (NASA)"
        ]
      }
    },
    {
      "title": "BFVH23DATADASH/Datadashboards",
      "start": "2024-12-02T12:30:00",
      "end": "2024-12-02T16:30:00",
      "extendedProps": {
        "groups": [
          "BFV2"
        ],
        "rooms": [
          "ZP11/H1.122"
        ],
        "lecturers": [
          "AM Poortinga (PARN)"
        ]
      }
    },
    {
      "title": "BFVH23DATADASH/Datadashboards",
      "start": "2024-12-03T08:30:00",
      "end": "2024-12-03T12:30:00",
      "extendedProps": {
        "groups": [
          "BFV2"
        ],
        "rooms": [
          "ZP11/H1.122"
        ],
        "lecturers": [
          "MA Noback (NOMI)"
        ]
      }
    },
    {
      "title": "BFVH23IMMUNO/Immunologie",
      "start": "2024-12-03T12:30:00",
      "end": "2024-12-03T16:30:00",
      "extendedProps": {
        "groups": [
          "BFV2"
        ],
        "rooms": [
          "ZP11/H1.122"
        ],
        "lecturers": [
          "L Oldhoff (OLLO)"
        ]
      }
    },
    {
      "title": "BFVH23DATADASH/Datadashboards",
      "start": "2024-12-04T08:30:00",
      "end": "2024-12-04T12:30:00",
      "extendedProps": {
        "groups": [
          "BFV2"
        ],
        "rooms": [
          "ZP11/H1.122"
        ],
        "lecturers": [
          "MA Noback (NOMI)"
        ]
      }
    },
    {
      "title": "BFVH23DATADASH/Datadashboards",
      "start": "2024-12-05T12:30:00",
      "end": "2024-12-05T16:30:00",
      "extendedProps": {
        "groups": [
          "BFV2"
        ],
        "rooms": [
          "ZP11/D1.08"
        ],
        "lecturers": [
          "B Barnard (BABA)"
        ]
      }
    },
    {
      "title": "BFVH23IMMUNO/Immunologie",
      "start": "2024-12-06T08:30:00",
      "end": "2024-12-06T12:30:00",
      "extendedProps": {
        "groups": [
          "BFV2"
        ],
        "rooms": [
          "ZP11/H1.122"
        ],
        "lecturers": [
          "SM Nabuurs (NASA)"
        ]
      }
    },
    {
      "title": "BFVH23DATADASH/Datadashboards",
      "start": "2024-12-09T12:30:00",
      "end": "2024-12-09T16:30:00",
      "extendedProps": {
        "groups": [
          "BFV2"
        ],
        "rooms": [
          "ZP11/H1.122"
        ],
        "lecturers": [
          "AM Poortinga (PARN)"
        ]
      }
    },
    {
      "title": "BFVH23DATADASH/Datadashboards",
      "start": "2024-12-10T08:30:00",
      "end": "2024-12-10T11:30:00",
      "extendedProps": {
        "groups": [
          "BFV2"
        ],
        "rooms": [
          "ZP11/H1.122"
        ],
        "lecturers": [
          "MA Noback (NOMI)"
        ]
      }
    },
    {
      "title": "Klassengesprek/Klassengesprek BFV2",
      "start": "2024-12-10T11:30:00",
      "end": "2024-12-10T12:30:00",
      "extendedProps": {
        "groups": [
          "BFV2"
        ],
        "rooms": [
          "ZP11/H1.122"
        ],
        "lecturers": [
          "MA Noback (NOMI)",
          "IM van der Veen (VEID)"
        ]
      }
    },
    {
      "title": "BFVH23IMMUNO/Immunologie",
      "start": "2024-12-10T12:30:00",
      "end": "2024-12-10T16:30:00",
      "extendedProps": {
        "groups": [
          "BFV2"
        ],
        "rooms": [
          "ZP11/H1.122"
        ],
        "lecturers": [
          "L Oldhoff (OLLO)"
        ]
      }
    },
    {
      "title": "BFVH23DATADASH/Datadashboards",
      "start": "2024-12-11T08:30:00",
      "end": "2024-12-11T12:30:00",
      "extendedProps": {
        "groups": [
          "BFV2"
        ],
        "rooms": [
          "ZP11/H1.122"
        ],
        "lecturers": [
          "B Barnard (BABA)"
        ]
      }
    },
    {
      "title": "BFVH23IMMUNO/Immunologie",
      "start": "2024-12-11T14:30:00",
      "end": "2024-12-11T16:30:00",
      "extendedProps": {
        "groups": [
          "BFV2"
        ],
        "rooms": [
          "ZP11/H1.122"
        ],
        "lecturers": [
          "SM Nabuurs (NASA)"
        ]
      }
    },
    {
      "title": "BFVH23DATADASH/Datadashboards",
      "start": "2024-12-12T12:30:00",
      "end": "2024-12-12T16:30:00",
      "extendedProps": {
        "groups": [
          "BFV2"
        ],
        "rooms": [
          "ZP11/D1.08"
        ],
        "lecturers": [
          "B Barnard (BABA)"
        ]
      }
    },
    {
      "title": "BFVH23DATADASH/Datadashboards",
      "start": "2024-12-16T12:30:00",
      "end": "2024-12-16T16:30:00",
      "extendedProps": {
        "groups": [
          "BFV2"
        ],
        "rooms": [
          "ZP11/H1.122"
        ],
        "lecturers": [
          "AM Poortinga (PARN)"
        ]
      }
    },
    {
      "title": "BFVH23DATADASH/Datadashboards",
      "start": "2024-12-17T08:30:00",
      "end": "2024-12-17T12:30:00",
      "extendedProps": {
        "groups": [
          "BFV2"
        ],
        "rooms": [
          "ZP11/H1.122"
        ],
        "lecturers": [
          "MA Noback (NOMI)"
        ]
      }
    },
    {
      "title": "BFVH23IMMUNO/Immunologie",
      "start": "2024-12-17T12:30:00",
      "end": "2024-12-17T16:30:00",
      "extendedProps": {
        "groups": [
          "BFV2"
        ],
        "rooms": [
          "ZP11/H1.122"
        ],
        "lecturers": [
          "L Oldhoff (OLLO)"
        ]
      }
    },
    {
      "title": "BFVH23DATADASH/Datadashboards",
      "start": "2024-12-18T08:30:00",
      "end": "2024-12-18T12:30:00",
      "extendedProps": {
        "groups": [
          "BFV2"
        ],
        "rooms": [
          "ZP11/H1.122"
        ],
        "lecturers": [
          "MA Noback (NOMI)"
        ]
      }
    },
    {
      "title": "BFVH23IMMUNO/Immunologie",
      "start": "2024-12-20T08:30:00",
      "end": "2024-12-20T12:30:00",
      "extendedProps": {
        "groups": [
          "BFV2"
        ],
        "rooms": [
          "ZP11/H1.122"
        ],
        "lecturers": [
          "SM Nabuurs (NASA)"
        ]
      }
    },
    {
      "title": "BFVH23DATADASH/Datadashboards",
      "start": "2025-01-06T12:30:00",
      "end": "2025-01-06T16:30:00",
      "extendedProps": {
        "groups": [
          "BFV2"
        ],
        "rooms": [
          "ZP11/H1.122"
        ],
        "lecturers": [
          "AM Poortinga (PARN)"
        ]
      }
    },
    {
      "title": "BFVH23DATADASH/Datadashboards",
      "start": "2025-01-07T08:30:00",
      "end": "2025-01-07T12:30:00",
      "extendedProps": {
        "groups": [
          "BFV2"
        ],
        "rooms": [
          "ZP11/H1.122"
        ],
        "lecturers": [
          "MA Noback (NOMI)"
        ]
      }
    },
    {
      "title": "BFVH23DATADASH/Datadashboards",
      "start": "2025-01-08T08:30:00",
      "end": "2025-01-08T12:30:00",
      "extendedProps": {
        "groups": [
          "BFV2"
        ],
        "rooms": [
          "ZP11/H1.122"
        ],
        "lecturers": [
          "B Barnard (BABA)"
        ]
      }
    },
    {
      "title": "BFVH23IMMUNO/Immunologie",
      "start": "2025-01-08T12:30:00",
      "end": "2025-01-08T16:30:00",
      "extendedProps": {
        "groups": [
          "BFV2"
        ],
        "rooms": [
          "ZP11/H1.122"
        ],
        "lecturers": [
          "SM Nabuurs (NASA)"
        ]
      }
    },
    {
      "title": "BFVH23DATADASH/Datadashboards",
      "start": "2025-01-10T08:30:00",
      "end": "2025-01-10T12:30:00",
      "extendedProps": {
        "groups": [
          "BFV2"
        ],
        "rooms": [
          "ZP11/H1.122"
        ],
        "lecturers": [
          "B Barnard (BABA)"
        ]
      }
    },
    {
      "title": "BFVH23IMMUNO/Immunologie",
      "start": "2025-01-10T12:30:00",
      "end": "2025-01-10T16:30:00",
      "extendedProps": {
        "groups": [
          "BFV2"
        ],
        "rooms": [
          "ZP11/D1.08"
        ],
        "lecturers": [
          "L Oldhoff (OLLO)"
        ]
      }
    },
    {
      "title": "BFVH23DATADASH/Datadashboards",
      "start": "2025-01-13T12:30:00",
      "end": "2025-01-13T16:30:00",
      "extendedProps": {
        "groups": [
          "BFV2"
        ],
        "rooms": [
          "ZP11/H1.122"
        ],
        "lecturers": [
          "AM Poortinga (PARN)"
        ]
      }
    },
    {
      "title": "BFVH23DATADASH/Datadashboards",
      "start": "2025-01-14T08:30:00",
      "end": "2025-01-14T12:30:00",
      "extendedProps": {
        "groups": [
          "BFV2"
        ],
        "rooms": [
          "ZP11/H1.122"
        ],
        "lecturers": [
          "MA Noback (NOMI)"
        ]
      }
    },
    {
      "title": "BFVH23IMMUNO/Immunologie",
      "start": "2025-01-14T12:30:00",
      "end": "2025-01-14T16:30:00",
      "extendedProps": {
        "groups": [
          "BFV2"
        ],
        "rooms": [
          "ZP11/H1.122"
        ],
        "lecturers": [
          "L Oldhoff (OLLO)"
        ]
      }
    },
    {
      "title": "BFVH23DATADASH/Datadashboards",
      "start": "2025-01-15T08:30:00",
      "end": "2025-01-15T12:30:00",
      "extendedProps": {
        "groups": [
          "BFV2"
        ],
        "rooms": [
          "ZP11/H1.122"
        ],
        "lecturers": [
          "MA Noback (NOMI)"
        ]
      }
    },
    {
      "title": "BFVH23IMMUNO/Immunologie",
      "start": "2025-01-15T12:30:00",
      "end": "2025-01-15T16:30:00",
      "extendedProps": {
        "groups": [
          "BFV2"
        ],
        "rooms": [
          "ZP11/H1.122"
        ],
        "lecturers": [
          "SM Nabuurs (NASA)"
        ]
      }
    },
    {
      "title": "BFVH23DATADASH/Datadashboards",
      "start": "2025-01-17T08:30:00",
      "end": "2025-01-17T12:30:00",
      "extendedProps": {
        "groups": [
          "BFV2"
        ],
        "rooms": [
          "ZP11/H1.122"
        ],
        "lecturers": [
          "B Barnard (BABA)"
        ]
      }
    },
    {
      "title": "BFVM23DSPH/Omics Research Project",
      "start": "2024-11-26T08:30:00",
      "end": "2024-11-26T10:30:00",
      "extendedProps": {
        "groups": [
          "DSLSR1"
        ],
        "rooms": [
          "ZP11/H1.86"
        ],
        "lecturers": [
          "M Herber (HEMI)",
          "M Kempenaar (KEMC)"
        ]
      }
    },
    {
      "title": "BFVM23DATASCNC2/Bayesian Statistics",
      "start": "2024-11-26T10:30:00",
      "end": "2024-11-26T12:30:00",
      "extendedProps": {
        "groups": [
          "DSLSR1"
        ],
        "rooms": [
          "ZP11/H1.86"
        ],
        "lecturers": [
          "MEF Apol (APMA)"
        ]
      }
    },
    {
      "title": "BFVM23DATASCNC2/Numerical Analysis",
      "start": "2024-11-26T12:30:00",
      "end": "2024-11-26T14:30:00",
      "extendedProps": {
        "groups": [
          "DSLSR1"
        ],
        "rooms": [
          "ZP11/H1.86"
        ],
        "lecturers": [
          "DRM Langers (LADR)"
        ]
      }
    },
    {
      "title": "BFVM23DATASCNC2/Numerical Analysis",
      "start": "2024-11-26T14:30:00",
      "end": "2024-11-26T16:30:00",
      "extendedProps": {
        "groups": [
          "DSLSR1"
        ],
        "rooms": [
          "ZP11/H1.86"
        ],
        "lecturers": [
          "DRM Langers (LADR)"
        ]
      }
    },
    {
      "title": "BFVM23PROGRAM2/Programming II",
      "start": "2024-11-27T08:30:00",
      "end": "2024-11-27T12:30:00",
      "extendedProps": {
        "groups": [
          "DSLSR1"
        ],
        "rooms": [
          "ZP11/H1.86"
        ],
        "lecturers": [
          "P C Kroon (KRPE)"
        ]
      }
    },
    {
      "title": "BFVM23DATASCNC2/Bayesian Statistics",
      "start": "2024-11-27T12:30:00",
      "end": "2024-11-27T14:30:00",
      "extendedProps": {
        "groups": [
          "DSLSR1"
        ],
        "rooms": [
          "ZP11/H1.86"
        ],
        "lecturers": [
          "MEF Apol (APMA)"
        ]
      }
    },
    {
      "title": "BFVM23DSPH/Omics Research Project",
      "start": "2024-11-28T08:30:00",
      "end": "2024-11-28T12:30:00",
      "extendedProps": {
        "groups": [
          "DSLSR1"
        ],
        "rooms": [
          "ZP11/H1.86"
        ],
        "lecturers": [
          "M Herber (HEMI)",
          "M Kempenaar (KEMC)"
        ]
      }
    },
    {
      "title": "BFVM23PROGRAM2/Programming II",
      "start": "2024-11-29T12:30:00",
      "end": "2024-11-29T16:30:00",
      "extendedProps": {
        "groups": [
          "DSLSR1"
        ],
        "rooms": [
          "ZP11/H1.86"
        ],
        "lecturers": [
          "F Feenstra (FEFE)",
          "M Kempenaar (KEMC)"
        ]
      }
    },
    {
      "title": "BFVM23DSPH/Omics Research Project",
      "start": "2024-12-03T08:30:00",
      "end": "2024-12-03T10:30:00",
      "extendedProps": {
        "groups": [
          "DSLSR1"
        ],
        "rooms": [
          "ZP11/H1.86"
        ],
        "lecturers": [
          "M Herber (HEMI)",
          "M Kempenaar (KEMC)"
        ]
      }
    },
    {
      "title": "BFVM23RPS/Sc. Reading & Writing",
      "start": "2024-12-03T10:30:00",
      "end": "2024-12-03T12:30:00",
      "extendedProps": {
        "groups": [
          "DSLSR1"
        ],
        "rooms": [
          "ZP11/H1.86"
        ],
        "lecturers": [
          "SM Nabuurs (NASA)"
        ]
      }
    },
    {
      "title": "BFVM23DATASCNC2/Numerical Analysis",
      "start": "2024-12-03T12:30:00",
      "end": "2024-12-03T14:30:00",
      "extendedProps": {
        "groups": [
          "DSLSR1"
        ],
        "rooms": [
          "ZP11/H1.86"
        ],
        "lecturers": [
          "DRM Langers (LADR)"
        ]
      }
    },
    {
      "title": "BFVM23DATASCNC2/Numerical Analysis",
      "start": "2024-12-03T14:30:00",
      "end": "2024-12-03T16:30:00",
      "extendedProps": {
        "groups": [
          "DSLSR1"
        ],
        "rooms": [
          "ZP11/H1.86"
        ],
        "lecturers": [
          "DRM Langers (LADR)"
        ]
      }
    },
    {
      "title": "BFVM23PROGRAM2/Programming II",
      "start": "2024-12-04T08:30:00",
      "end": "2024-12-04T12:30:00",
      "extendedProps": {
        "groups": [
          "DSLSR1"
        ],
        "rooms": [
          "ZP11/H1.86"
        ],
        "lecturers": [
          "P C Kroon (KRPE)"
        ]
      }
    },
    {
      "title": "BFVM23DATASCNC2/Bayesian Statistics",
      "start": "2024-12-04T12:30:00",
      "end": "2024-12-04T14:30:00",
      "extendedProps": {
        "groups": [
          "DSLSR1"
        ],
        "rooms": [
          "ZP11/H1.86"
        ],
        "lecturers": [
          "MEF Apol (APMA)"
        ]
      }
    },
    {
      "title": "BFVM23DATASCNC2/Bayesian Statistics",
      "start": "2024-12-04T14:30:00",
      "end": "2024-12-04T16:30:00",
      "extendedProps": {
        "groups": [
          "DSLSR1"
        ],
        "rooms": [
          "ZP11/H1.86"
        ],
        "lecturers": [
          "MEF Apol (APMA)"
        ]
      }
    },
    {
      "title": "BFVM23DSPH/Omics Research Project",
      "start": "2024-12-05T08:30:00",
      "end": "2024-12-05T12:30:00",
      "extendedProps": {
        "groups": [
          "DSLSR1"
        ],
        "rooms": [
          "ZP11/H1.86"
        ],
        "lecturers": [
          "M Herber (HEMI)",
          "M Kempenaar (KEMC)"
        ]
      }
    },
    {
      "title": "BFVM23PROGRAM2/Programming II",
      "start": "2024-12-06T12:30:00",
      "end": "2024-12-06T16:30:00",
      "extendedProps": {
        "groups": [
          "DSLSR1"
        ],
        "rooms": [
          "ZP11/H1.86"
        ],
        "lecturers": [
          "F Feenstra (FEFE)",
          "M Kempenaar (KEMC)"
        ]
      }
    },
    {
      "title": "BFVM23DSPH/Omics Research Project",
      "start": "2024-12-10T08:30:00",
      "end": "2024-12-10T10:30:00",
      "extendedProps": {
        "groups": [
          "DSLSR1"
        ],
        "rooms": [
          "ZP11/H1.86"
        ],
        "lecturers": [
          "M Herber (HEMI)",
          "M Kempenaar (KEMC)"
        ]
      }
    },
    {
      "title": "BFVM23DATASCNC2/Bayesian Statistics",
      "start": "2024-12-10T10:30:00",
      "end": "2024-12-10T12:30:00",
      "extendedProps": {
        "groups": [
          "DSLSR1"
        ],
        "rooms": [
          "ZP11/H1.86"
        ],
        "lecturers": [
          "MEF Apol (APMA)"
        ]
      }
    },
    {
      "title": "BFVM23DATASCNC2/Numerical Analysis",
      "start": "2024-12-10T12:30:00",
      "end": "2024-12-10T14:30:00",
      "extendedProps": {
        "groups": [
          "DSLSR1"
        ],
        "rooms": [
          "ZP11/H1.86"
        ],
        "lecturers": [
          "DRM Langers (LADR)"
        ]
      }
    },
    {
      "title": "BFVM23DATASCNC2/Numerical Analysis",
      "start": "2024-12-10T14:30:00",
      "end": "2024-12-10T16:30:00",
      "extendedProps": {
        "groups": [
          "DSLSR1"
        ],
        "rooms": [
          "ZP11/H1.86"
        ],
        "lecturers": [
          "DRM Langers (LADR)"
        ]
      }
    },
    {
      "title": "BFVM23PROGRAM2/Programming II",
      "start": "2024-12-11T08:30:00",
      "end": "2024-12-11T12:30:00",
      "extendedProps": {
        "groups": [
          "DSLSR1"
        ],
        "rooms": [
          "ZP11/H1.86"
        ],
        "lecturers": [
          "P C Kroon (KRPE)"
        ]
      }
    },
    {
      "title": "BFVM23DATASCNC2/Bayesian Statistics",
      "start": "2024-12-11T12:30:00",
      "end": "2024-12-11T14:30:00",
      "extendedProps": {
        "groups": [
          "DSLSR1"
        ],
        "rooms": [
          "ZP11/H1.86"
        ],
        "lecturers": [
          "MEF Apol (APMA)"
        ]
      }
    },
    {
      "title": "BFVM23DSPH/Omics Research Project",
      "start": "2024-12-12T08:30:00",
      "end": "2024-12-12T12:30:00",
      "extendedProps": {
        "groups": [
          "DSLSR1"
        ],
        "rooms": [
          "ZP11/H1.86"
        ],
        "lecturers": [
          "M Herber (HEMI)",
          "M Kempenaar (KEMC)"
        ]
      }
    },
    {
      "title": "BFVM23PROGRAM2/Programming II",
      "start": "2024-12-13T12:30:00",
      "end": "2024-12-13T16:30:00",
      "extendedProps": {
        "groups": [
          "DSLSR1"
        ],
        "rooms": [
          "ZP11/H1.86"
        ],
        "lecturers": [
          "F Feenstra (FEFE)",
          "M Kempenaar (KEMC)"
        ]
      }
    },
    {
      "title": "BFVM23DSPH/Omics Research Project",
      "start": "2024-12-17T08:30:00",
      "end": "2024-12-17T10:30:00",
      "extendedProps": {
        "groups": [
          "DSLSR1"
        ],
        "rooms": [
          "ZP11/H1.86"
        ],
        "lecturers": [
          "M Herber (HEMI)",
          "M Kempenaar (KEMC)"
        ]
      }
    },
    {
      "title": "BFVM23DATASCNC2/Numerical Analysis",
      "start": "2024-12-17T10:30:00",
      "end": "2024-12-17T12:30:00",
      "extendedProps": {
        "groups": [
          "DSLSR1"
        ],
        "rooms": [
          "ZP11/H1.86"
        ],
        "lecturers": [
          "DRM Langers (LADR)"
        ]
      }
    },
    {
      "title": "BFVM23DATASCNC2/Numerical Analysis",
      "start": "2024-12-17T12:30:00",
      "end": "2024-12-17T14:30:00",
      "extendedProps": {
        "groups": [
          "DSLSR1"
        ],
        "rooms": [
          "ZP11/H1.86"
        ],
        "lecturers": [
          "DRM Langers (LADR)"
        ]
      }
    },
    {
      "title": "BFVM23PROGRAM2/Programming II",
      "start": "2024-12-18T08:30:00",
      "end": "2024-12-18T12:30:00",
      "extendedProps": {
        "groups": [
          "DSLSR1"
        ],
        "rooms": [
          "ZP11/H1.86"
        ],
        "lecturers": [
          "P C Kroon (KRPE)"
        ]
      }
    },
    {
      "title": "BFVM23DATASCNC2/Bayesian Statistics",
      "start": "2024-12-18T12:30:00",
      "end": "2024-12-18T14:30:00",
      "extendedProps": {
        "groups": [
          "DSLSR1"
        ],
        "rooms": [
          "ZP11/H1.86"
        ],
        "lecturers": [
          "MEF Apol (APMA)"
        ]
      }
    },
    {
      "title": "BFVM23DATASCNC2/Bayesian Statistics",
      "start": "2024-12-18T14:30:00",
      "end": "2024-12-18T16:30:00",
      "extendedProps": {
        "groups": [
          "DSLSR1"
        ],
        "rooms": [
          "ZP11/H1.86"
        ],
        "lecturers": [
          "MEF Apol (APMA)"
        ]
      }
    },
    {
      "title": "BFVM23DSPH/Omics Research Project",
      "start": "2024-12-19T08:30:00",
      "end": "2024-12-19T12:30:00",
      "extendedProps": {
        "groups": [
          "DSLSR1"
        ],
        "rooms": [
          "ZP11/H1.86"
        ],
        "lecturers": [
          "M Herber (HEMI)",
          "M Kempenaar (KEMC)"
        ]
      }
    },
    {
      "title": "BFVM23PROGRAM2/Programming II",
      "start": "2024-12-20T12:30:00",
      "end": "2024-12-20T16:30:00",
      "extendedProps": {
        "groups": [
          "DSLSR1"
        ],
        "rooms": [
          "ZP11/H1.86"
        ],
        "lecturers": [
          "F Feenstra (FEFE)",
          "M Kempenaar (KEMC)"
        ]
      }
    },
    {
      "title": "BFVM23DSPH/Omics Research Project",
      "start": "2025-01-07T08:30:00",
      "end": "2025-01-07T10:30:00",
      "extendedProps": {
        "groups": [
          "DSLSR1"
        ],
        "rooms": [
          "ZP11/H1.86"
        ],
        "lecturers": [
          "M Herber (HEMI)",
          "M Kempenaar (KEMC)"
        ]
      }
    },
    {
      "title": "BFVM23DATASCNC2/Numerical Analysis",
      "start": "2025-01-07T10:30:00",
      "end": "2025-01-07T12:30:00",
      "extendedProps": {
        "groups": [
          "DSLSR1"
        ],
        "rooms": [
          "ZP11/H1.86"
        ],
        "lecturers": [
          "DRM Langers (LADR)"
        ]
      }
    },
    {
      "title": "BFVM23DATASCNC2/Numerical Analysis",
      "start": "2025-01-07T12:30:00",
      "end": "2025-01-07T14:30:00",
      "extendedProps": {
        "groups": [
          "DSLSR1"
        ],
        "rooms": [
          "ZP11/H1.86"
        ],
        "lecturers": [
          "DRM Langers (LADR)"
        ]
      }
    },
    {
      "title": "BFVM23PROGRAM2/Programming II",
      "start": "2025-01-08T08:30:00",
      "end": "2025-01-08T12:30:00",
      "extendedProps": {
        "groups": [
          "DSLSR1"
        ],
        "rooms": [
          "ZP11/H1.86"
        ],
        "lecturers": [
          "M Kempenaar (KEMC)"
        ]
      }
    },
    {
      "title": "BFVM23DATASCNC2/Bayesian Statistics",
      "start": "2025-01-08T12:30:00",
      "end": "2025-01-08T14:30:00",
      "extendedProps": {
        "groups": [
          "DSLSR1"
        ],
        "rooms": [
          "ZP11/H1.86"
        ],
        "lecturers": [
          "MEF Apol (APMA)"
        ]
      }
    },
    {
      "title": "BFVM23DATASCNC2/Bayesian Statistics",
      "start": "2025-01-08T14:30:00",
      "end": "2025-01-08T16:30:00",
      "extendedProps": {
        "groups": [
          "DSLSR1"
        ],
        "rooms": [
          "ZP11/H1.86"
        ],
        "lecturers": [
          "MEF Apol (APMA)"
        ]
      }
    },
    {
      "title": "BFVM23DSPH/Omics Research Project",
      "start": "2025-01-09T08:30:00",
      "end": "2025-01-09T12:30:00",
      "extendedProps": {
        "groups": [
          "DSLSR1"
        ],
        "rooms": [
          "ZP11/H1.86"
        ],
        "lecturers": [
          "M Herber (HEMI)",
          "M Kempenaar (KEMC)"
        ]
      }
    },
    {
      "title": "BFVM23PROGRAM2/Programming II",
      "start": "2025-01-10T12:30:00",
      "end": "2025-01-10T16:30:00",
      "extendedProps": {
        "groups": [
          "DSLSR1"
        ],
        "rooms": [
          "ZP11/H1.86"
        ],
        "lecturers": [
          "F Feenstra (FEFE)",
          "M Kempenaar (KEMC)"
        ]
      }
    },
    {
      "title": "BFVM23DSPH/Omics Research Project",
      "start": "2025-01-14T08:30:00",
      "end": "2025-01-14T10:30:00",
      "extendedProps": {
        "groups": [
          "DSLSR1"
        ],
        "rooms": [
          "ZP11/H1.86"
        ],
        "lecturers": [
          "M Herber (HEMI)",
          "M Kempenaar (KEMC)"
        ]
      }
    },
    {
      "title": "BFVM23RPS/Sc. Reading & Writing",
      "start": "2025-01-14T10:30:00",
      "end": "2025-01-14T12:30:00",
      "extendedProps": {
        "groups": [
          "DSLSR1"
        ],
        "rooms": [
          "ZP11/H1.86"
        ],
        "lecturers": [
          "SM Nabuurs (NASA)"
        ]
      }
    },
    {
      "title": "BFVM23DATASCNC2/Numerical Analysis",
      "start": "2025-01-14T12:30:00",
      "end": "2025-01-14T14:30:00",
      "extendedProps": {
        "groups": [
          "DSLSR1"
        ],
        "rooms": [
          "ZP11/H1.86"
        ],
        "lecturers": [
          "DRM Langers (LADR)"
        ]
      }
    },
    {
      "title": "BFVM23DATASCNC2/Numerical Analysis",
      "start": "2025-01-14T14:30:00",
      "end": "2025-01-14T16:30:00",
      "extendedProps": {
        "groups": [
          "DSLSR1"
        ],
        "rooms": [
          "ZP11/H1.86"
        ],
        "lecturers": [
          "DRM Langers (LADR)"
        ]
      }
    },
    {
      "title": "BFVM23PROGRAM2/Programming II",
      "start": "2025-01-15T08:30:00",
      "end": "2025-01-15T12:30:00",
      "extendedProps": {
        "groups": [
          "DSLSR1"
        ],
        "rooms": [
          "ZP11/H1.86"
        ],
        "lecturers": [
          "M Kempenaar (KEMC)"
        ]
      }
    },
    {
      "title": "BFVM23DATASCNC2/Bayesian Statistics",
      "start": "2025-01-15T12:30:00",
      "end": "2025-01-15T14:30:00",
      "extendedProps": {
        "groups": [
          "DSLSR1"
        ],
        "rooms": [
          "ZP11/H1.86"
        ],
        "lecturers": [
          "MEF Apol (APMA)"
        ]
      }
    },
    {
      "title": "BFVM23DSPH/Omics Research Project",
      "start": "2025-01-16T08:30:00",
      "end": "2025-01-16T12:30:00",
      "extendedProps": {
        "groups": [
          "DSLSR1"
        ],
        "rooms": [
          "ZP11/H1.86"
        ],
        "lecturers": [
          "M Herber (HEMI)",
          "M Kempenaar (KEMC)"
        ]
      }
    },
    {
      "title": "BFVM23PROGRAM2/Programming II",
      "start": "2025-01-17T12:30:00",
      "end": "2025-01-17T16:30:00",
      "extendedProps": {
        "groups": [
          "DSLSR1"
        ],
        "rooms": [
          "ZP11/H1.86"
        ],
        "lecturers": [
          "F Feenstra (FEFE)",
          "M Kempenaar (KEMC)"
        ]
      }
    },
    {
      "title": "BFVM23DATASCNC6/Unsupervised Learning",
      "start": "2024-11-25T08:30:00",
      "end": "2024-11-25T10:30:00",
      "extendedProps": {
        "groups": [
          "DSLSR2"
        ],
        "rooms": [
          "ZP11/H1.86"
        ],
        "lecturers": [
          "F Feenstra (FEFE)"
        ]
      }
    },
    {
      "title": "BFVM23DATASCNC6/Unsupervised Learning",
      "start": "2024-11-25T10:30:00",
      "end": "2024-11-25T12:30:00",
      "extendedProps": {
        "groups": [
          "DSLSR2"
        ],
        "rooms": [
          "ZP11/H1.86"
        ],
        "lecturers": [
          "F Feenstra (FEFE)"
        ]
      }
    },
    {
      "title": "BFVM23PROGRAM6/Programming VI",
      "start": "2024-11-25T12:30:00",
      "end": "2024-11-25T14:30:00",
      "extendedProps": {
        "groups": [
          "DSLSR2"
        ],
        "rooms": [
          "ZP11/H1.86"
        ],
        "lecturers": [
          "F Feenstra (FEFE)"
        ]
      }
    },
    {
      "title": "BFVM23RPS/Scientific Writing",
      "start": "2024-11-25T14:30:00",
      "end": "2024-11-25T16:30:00",
      "extendedProps": {
        "groups": [
          "DSLSR2"
        ],
        "rooms": [
          "ZP11/H1.86"
        ],
        "lecturers": [
          "TA Wassenaar (WATS)"
        ]
      }
    },
    {
      "title": "BFVM23DATASCNC6/Unsupervised Learning",
      "start": "2024-11-29T08:30:00",
      "end": "2024-11-29T10:30:00",
      "extendedProps": {
        "groups": [
          "DSLSR2"
        ],
        "rooms": [
          "ZP11/H1.86"
        ],
        "lecturers": [
          "F Feenstra (FEFE)"
        ]
      }
    },
    {
      "title": "BFVM23PROGRAM6/Programming VI",
      "start": "2024-11-29T10:30:00",
      "end": "2024-11-29T12:30:00",
      "extendedProps": {
        "groups": [
          "DSLSR2"
        ],
        "rooms": [
          "ZP11/H1.86"
        ],
        "lecturers": [
          "F Feenstra (FEFE)"
        ]
      }
    },
    {
      "title": "BFVM23DATASCNC6/Unsupervised Learning",
      "start": "2024-12-02T08:30:00",
      "end": "2024-12-02T10:30:00",
      "extendedProps": {
        "groups": [
          "DSLSR2"
        ],
        "rooms": [
          "ZP11/H1.86"
        ],
        "lecturers": [
          "F Feenstra (FEFE)"
        ]
      }
    },
    {
      "title": "BFVM23DATASCNC6/Unsupervised Learning",
      "start": "2024-12-02T10:30:00",
      "end": "2024-12-02T12:30:00",
      "extendedProps": {
        "groups": [
          "DSLSR2"
        ],
        "rooms": [
          "ZP11/H1.86"
        ],
        "lecturers": []
      }
    },
    {
      "title": "BFVM23PROGRAM6/Programming VI",
      "start": "2024-12-02T12:30:00",
      "end": "2024-12-02T14:30:00",
      "extendedProps": {
        "groups": [
          "DSLSR2"
        ],
        "rooms": [
          "ZP11/H1.86"
        ],
        "lecturers": [
          "F Feenstra (FEFE)"
        ]
      }
    },
    {
      "title": "BFVM23RPS/Scientific Writing",
      "start": "2024-12-02T14:30:00",
      "end": "2024-12-02T16:30:00",
      "extendedProps": {
        "groups": [
          "DSLSR2"
        ],
        "rooms": [
          "ZP11/H1.86"
        ],
        "lecturers": [
          "TA Wassenaar (WATS)"
        ]
      }
    },
    {
      "title": "BFVM23DATASCNC6/Unsupervised Learning",
      "start": "2024-12-06T08:30:00",
      "end": "2024-12-06T10:30:00",
      "extendedProps": {
        "groups": [
          "DSLSR2"
        ],
        "rooms": [
          "ZP11/H1.86"
        ],
        "lecturers": [
          "F Feenstra (FEFE)"
        ]
      }
    },
    {
      "title": "BFVM23PROGRAM6/Programming VI",
      "start": "2024-12-06T10:30:00",
      "end": "2024-12-06T12:30:00",
      "extendedProps": {
        "groups": [
          "DSLSR2"
        ],
        "rooms": [
          "ZP11/H1.86"
        ],
        "lecturers": [
          "F Feenstra (FEFE)"
        ]
      }
    },
    {
      "title": "BFVM23DATASCNC6/Unsupervised Learning",
      "start": "2024-12-09T08:30:00",
      "end": "2024-12-09T10:30:00",
      "extendedProps": {
        "groups": [
          "DSLSR2"
        ],
        "rooms": [
          "ZP11/H1.86"
        ],
        "lecturers": [
          "F Feenstra (FEFE)"
        ]
      }
    },
    {
      "title": "BFVM23DATASCNC6/Unsupervised Learning",
      "start": "2024-12-09T10:30:00",
      "end": "2024-12-09T12:30:00",
      "extendedProps": {
        "groups": [
          "DSLSR2"
        ],
        "rooms": [
          "ZP11/H1.86"
        ],
        "lecturers": [
          "F Feenstra (FEFE)"
        ]
      }
    },
    {
      "title": "BFVM23PROGRAM6/Programming VI",
      "start": "2024-12-09T12:30:00",
      "end": "2024-12-09T14:30:00",
      "extendedProps": {
        "groups": [
          "DSLSR2"
        ],
        "rooms": [
          "ZP11/H1.86"
        ],
        "lecturers": [
          "F Feenstra (FEFE)"
        ]
      }
    },
    {
      "title": "BFVM23RPS/Scientific Writing",
      "start": "2024-12-09T14:30:00",
      "end": "2024-12-09T16:30:00",
      "extendedProps": {
        "groups": [
          "DSLSR2"
        ],
        "rooms": [
          "ZP11/H1.86"
        ],
        "lecturers": [
          "TA Wassenaar (WATS)"
        ]
      }
    },
    {
      "title": "BFVM23DATASCNC6/Unsupervised Learning",
      "start": "2024-12-13T08:30:00",
      "end": "2024-12-13T10:30:00",
      "extendedProps": {
        "groups": [
          "DSLSR2"
        ],
        "rooms": [
          "ZP11/H1.86"
        ],
        "lecturers": [
          "F Feenstra (FEFE)"
        ]
      }
    },
    {
      "title": "BFVM23PROGRAM6/Programming VI",
      "start": "2024-12-13T10:30:00",
      "end": "2024-12-13T12:30:00",
      "extendedProps": {
        "groups": [
          "DSLSR2"
        ],
        "rooms": [
          "ZP11/H1.86"
        ],
        "lecturers": []
      }
    },
    {
      "title": "BFVM23DATASCNC6/Deep Learning",
      "start": "2024-12-16T08:30:00",
      "end": "2024-12-16T10:30:00",
      "extendedProps": {
        "groups": [
          "DSLSR2"
        ],
        "rooms": [
          "ZP11/H1.86"
        ],
        "lecturers": [
          "F Feenstra (FEFE)"
        ]
      }
    },
    {
      "title": "BFVM23DATASCNC6/Deep Learning",
      "start": "2024-12-16T10:30:00",
      "end": "2024-12-16T12:30:00",
      "extendedProps": {
        "groups": [
          "DSLSR2"
        ],
        "rooms": [
          "ZP11/H1.86"
        ],
        "lecturers": [
          "F Feenstra (FEFE)"
        ]
      }
    },
    {
      "title": "BFVM23PROGRAM6/Programming VI",
      "start": "2024-12-16T12:30:00",
      "end": "2024-12-16T14:30:00",
      "extendedProps": {
        "groups": [
          "DSLSR2"
        ],
        "rooms": [
          "ZP11/H1.86"
        ],
        "lecturers": [
          "F Feenstra (FEFE)"
        ]
      }
    },
    {
      "title": "BFVM23RPS/Scientific Writing",
      "start": "2024-12-16T14:30:00",
      "end": "2024-12-16T16:30:00",
      "extendedProps": {
        "groups": [
          "DSLSR2"
        ],
        "rooms": [
          "ZP11/H1.86"
        ],
        "lecturers": [
          "TA Wassenaar (WATS)"
        ]
      }
    },
    {
      "title": "BFVM23DATASCNC6/Deep Learning",
      "start": "2024-12-20T08:30:00",
      "end": "2024-12-20T10:30:00",
      "extendedProps": {
        "groups": [
          "DSLSR2"
        ],
        "rooms": [
          "ZP11/H1.86"
        ],
        "lecturers": [
          "F Feenstra (FEFE)"
        ]
      }
    },
    {
      "title": "BFVM23PROGRAM6/Programming VI",
      "start": "2024-12-20T10:30:00",
      "end": "2024-12-20T12:30:00",
      "extendedProps": {
        "groups": [
          "DSLSR2"
        ],
        "rooms": [
          "ZP11/H1.86"
        ],
        "lecturers": [
          "F Feenstra (FEFE)"
        ]
      }
    },
    {
      "title": "BFVM23DATASCNC6/Deep Learning",
      "start": "2025-01-06T08:30:00",
      "end": "2025-01-06T10:30:00",
      "extendedProps": {
        "groups": [
          "DSLSR2"
        ],
        "rooms": [
          "ZP11/H1.86"
        ],
        "lecturers": [
          "DRM Langers (LADR)"
        ]
      }
    },
    {
      "title": "BFVM23DATASCNC6/Deep Learning",
      "start": "2025-01-06T10:30:00",
      "end": "2025-01-06T12:30:00",
      "extendedProps": {
        "groups": [
          "DSLSR2"
        ],
        "rooms": [
          "ZP11/H1.86"
        ],
        "lecturers": [
          "DRM Langers (LADR)"
        ]
      }
    },
    {
      "title": "BFVM23PROGRAM6/Programming VI",
      "start": "2025-01-06T12:30:00",
      "end": "2025-01-06T14:30:00",
      "extendedProps": {
        "groups": [
          "DSLSR2"
        ],
        "rooms": [
          "ZP11/H1.86"
        ],
        "lecturers": [
          "F Feenstra (FEFE)"
        ]
      }
    },
    {
      "title": "BFVM23RPS/Scientific Writing",
      "start": "2025-01-06T14:30:00",
      "end": "2025-01-06T16:30:00",
      "extendedProps": {
        "groups": [
          "DSLSR2"
        ],
        "rooms": [
          "ZP11/H1.86"
        ],
        "lecturers": [
          "TA Wassenaar (WATS)"
        ]
      }
    },
    {
      "title": "BFVM23DATASCNC6/Deep Learning",
      "start": "2025-01-10T08:30:00",
      "end": "2025-01-10T10:30:00",
      "extendedProps": {
        "groups": [
          "DSLSR2"
        ],
        "rooms": [
          "ZP11/H1.86"
        ],
        "lecturers": []
      }
    },
    {
      "title": "BFVM23PROGRAM6/Programming VI",
      "start": "2025-01-10T10:30:00",
      "end": "2025-01-10T12:30:00",
      "extendedProps": {
        "groups": [
          "DSLSR2"
        ],
        "rooms": [
          "ZP11/H1.86"
        ],
        "lecturers": [
          "F Feenstra (FEFE)"
        ]
      }
    },
    {
      "title": "BFVM23DATASCNC6/Deep Learning",
      "start": "2025-01-13T08:30:00",
      "end": "2025-01-13T10:30:00",
      "extendedProps": {
        "groups": [
          "DSLSR2"
        ],
        "rooms": [
          "ZP11/H1.86"
        ],
        "lecturers": [
          "DRM Langers (LADR)"
        ]
      }
    },
    {
      "title": "BFVM23DATASCNC6/Deep Learning",
      "start": "2025-01-13T10:30:00",
      "end": "2025-01-13T12:30:00",
      "extendedProps": {
        "groups": [
          "DSLSR2"
        ],
        "rooms": [
          "ZP11/H1.86"
        ],
        "lecturers": [
          "DRM Langers (LADR)"
        ]
      }
    },
    {
      "title": "BFVM23PROGRAM6/Programming VI",
      "start": "2025-01-13T12:30:00",
      "end": "2025-01-13T14:30:00",
      "extendedProps": {
        "groups": [
          "DSLSR2"
        ],
        "rooms": [
          "ZP11/H1.86"
        ],
        "lecturers": [
          "F Feenstra (FEFE)"
        ]
      }
    },
    {
      "title": "BFVM23RPS/Scientific Writing",
      "start": "2025-01-13T14:30:00",
      "end": "2025-01-13T16:30:00",
      "extendedProps": {
        "groups": [
          "DSLSR2"
        ],
        "rooms": [
          "ZP11/H1.86"
        ],
        "lecturers": [
          "TA Wassenaar (WATS)"
        ]
      }
    },
    {
      "title": "BFVM23DATASCNC6/Deep Learning",
      "start": "2025-01-17T08:30:00",
      "end": "2025-01-17T10:30:00",
      "extendedProps": {
        "groups": [
          "DSLSR2"
        ],
        "rooms": [
          "ZP11/H1.86"
        ],
        "lecturers": [
          "DRM Langers (LADR)"
        ]
      }
    },
    {
      "title": "BFVM23PROGRAM6/Programming VI",
      "start": "2025-01-17T10:30:00",
      "end": "2025-01-17T12:30:00",
      "extendedProps": {
        "groups": [
          "DSLSR2"
        ],
        "rooms": [
          "ZP11/H1.86"
        ],
        "lecturers": [
          "F Feenstra (FEFE)"
        ]
      }
    },
    {
      "title": "BIN middag",
      "start": "2024-11-28T12:00:00",
      "end": "2024-11-28T17:00:00",
      "extendedProps": {
        "groups": [],
        "rooms": [
          "ZP11/H1.122"
        ],
        "lecturers": [
          " (BLJA)",
          "J Bosman (BOJP)",
          "F Feenstra (FEFE)",
          "M Herber (HEMI)",
          "M Kempenaar (KEMC)",
          "P C Kroon (KRPE)",
          "DRM Langers (LADR)",
          "SM Nabuurs (NASA)",
          "MA Noback (NOMI)",
          "L Oldhoff (OLLO)",
          "AM Poortinga (PARN)",
          "WA Pool (POWE)",
          "IM van der Veen (VEID)",
          "TA Wassenaar (WATS)",
          "R Wedema (WERD)",
          "BD Williams (WIBA)"
        ]
      },
      "backgroundColor": "#464646",
      "borderColor": "#464646"
    },
    {
      "title": "BIN middag",
      "start": "2024-12-05T12:00:00",
      "end": "2024-12-05T17:00:00",
      "extendedProps": {
        "groups": [],
        "rooms": [
          "ZP11/H1.122"
        ],
        "lecturers": [
          " (BLJA)",
          "J Bosman (BOJP)",
          "F Feenstra (FEFE)",
          "M Herber (HEMI)",
          "M Kempenaar (KEMC)",
          "P C Kroon (KRPE)",
          "DRM Langers (LADR)",
          "SM Nabuurs (NASA)",
          "MA Noback (NOMI)",
          "L Oldhoff (OLLO)",
          "AM Poortinga (PARN)",
          "WA Pool (POWE)",
          "IM van der Veen (VEID)",
          "TA Wassenaar (WATS)",
          "R Wedema (WERD)",
          "BD Williams (WIBA)"
        ]
      },
      "backgroundColor": "#464646",
      "borderColor": "#464646"
    },
    {
      "title": "BIN middag",
      "start": "2024-12-19T12:00:00",
      "end": "2024-12-19T17:00:00",
      "extendedProps": {
        "groups": [],
        "rooms": [
          "ZP11/H1.122"
        ],
        "lecturers": [
          " (BLJA)",
          "J Bosman (BOJP)",
          "F Feenstra (FEFE)",
          "M Herber (HEMI)",
          "M Kempenaar (KEMC)",
          "P C Kroon (KRPE)",
          "DRM Langers (LADR)",
          "SM Nabuurs (NASA)",
          "MA Noback (NOMI)",
          "L Oldhoff (OLLO)",
          "AM Poortinga (PARN)",
          "WA Pool (POWE)",
          "IM van der Veen (VEID)",
          "TA Wassenaar (WATS)",
          "R Wedema (WERD)",
          "BD Williams (WIBA)"
        ]
      },
      "backgroundColor": "#464646",
      "borderColor": "#464646"
    },
    {
      "title": "BIN middag",
      "start": "2025-01-09T12:00:00",
      "end": "2025-01-09T17:00:00",
      "extendedProps": {
        "groups": [],
        "rooms": [
          "ZP11/H1.122"
        ],
        "lecturers": [
          " (BLJA)",
          "J Bosman (BOJP)",
          "F Feenstra (FEFE)",
          "M Herber (HEMI)",
          "M Kempenaar (KEMC)",
          "P C Kroon (KRPE)",
          "DRM Langers (LADR)",
          "SM Nabuurs (NASA)",
          "MA Noback (NOMI)",
          "L Oldhoff (OLLO)",
          "AM Poortinga (PARN)",
          "WA Pool (POWE)",
          "IM van der Veen (VEID)",
          "TA Wassenaar (WATS)",
          "R Wedema (WERD)",
          "BD Williams (WIBA)"
        ]
      },
      "backgroundColor": "#464646",
      "borderColor": "#464646"
    }
  ]
}